dspider/__init__.py
dspider/ctx.py
dspider/engine.py
dspider/httpclient.py
dspider/item.py
dspider/middleware.py
dspider/queue.py
dspider/request.py
dspider/response.py
dspider/spider.py
dspider/typedefs.py
dspider/utils.py
dspider-0.0.3.dist-info/LICENSE
dspider-0.0.3.dist-info/METADATA
dspider-0.0.3.dist-info/WHEEL
dspider-0.0.3.dist-info/top_level.txt
dspider-0.0.3.dist-info/RECORD
